<?xml version="1.0" encoding="UTF-8"?><record_update sys_domain="global" table="sys_script_client">
    <sys_script_client action="DELETE">
        <active>true</active>
        <applies_extended>false</applies_extended>
        <condition/>
        <description/>
        <field>project_name</field>
        <global>true</global>
        <isolate_script>true</isolate_script>
        <messages/>
        <name>Onchange </name>
        <order/>
        <script><![CDATA[function onChange(control, oldValue, newValue, isLoading, isTemplate) {
   if (isLoading || newValue === '') {
      return;
   }
	var old=g_form.getReference('project_name').Project_Name;
	var newv=g_form.getReference('project_name').Project_Name;
 alert('old');
	alert('newv');
   //Type appropriate comment here, and begin script below
   
}]]></script>
        <sys_class_name>sys_script_client</sys_class_name>
        <sys_created_by>admin</sys_created_by>
        <sys_created_on>2022-03-18 05:37:32</sys_created_on>
        <sys_domain>global</sys_domain>
        <sys_domain_path>/</sys_domain_path>
        <sys_id>9459207d1bd609105c68ec23604bcb42</sys_id>
        <sys_mod_count>4</sys_mod_count>
        <sys_name>Onchange </sys_name>
        <sys_overrides/>
        <sys_package display_value="Smart Management" source="x_775264_smart_man">0ad3d8e51b9ac5105c68ec23604bcb5f</sys_package>
        <sys_policy/>
        <sys_scope display_value="Smart Management">0ad3d8e51b9ac5105c68ec23604bcb5f</sys_scope>
        <sys_update_name>sys_script_client_9459207d1bd609105c68ec23604bcb42</sys_update_name>
        <sys_updated_by>admin</sys_updated_by>
        <sys_updated_on>2022-03-18 06:27:57</sys_updated_on>
        <table>x_775264_smart_man_project_details</table>
        <type>onChange</type>
        <ui_type>0</ui_type>
        <view/>
    </sys_script_client>
    <sys_update_version action="INSERT_OR_UPDATE">
        <action>DELETE</action>
        <application display_value="Smart Management">0ad3d8e51b9ac5105c68ec23604bcb5f</application>
        <file_path/>
        <instance_id>a456b0dc1b007410c8432f8dee4bcb3a</instance_id>
        <instance_name>dev113567</instance_name>
        <name>sys_script_client_9459207d1bd609105c68ec23604bcb42</name>
        <payload>&lt;?xml version="1.0" encoding="UTF-8"?&gt;&lt;record_update sys_domain="global" table="sys_script_client"&gt;&lt;sys_script_client action="INSERT_OR_UPDATE"&gt;&lt;active&gt;true&lt;/active&gt;&lt;applies_extended&gt;false&lt;/applies_extended&gt;&lt;condition/&gt;&lt;description/&gt;&lt;field&gt;project_name&lt;/field&gt;&lt;global&gt;true&lt;/global&gt;&lt;isolate_script&gt;true&lt;/isolate_script&gt;&lt;messages/&gt;&lt;name&gt;Onchange &lt;/name&gt;&lt;order/&gt;&lt;script&gt;&lt;![CDATA[function onChange(control, oldValue, newValue, isLoading, isTemplate) {
   if (isLoading || newValue === '') {
      return;
   }
	var old=g_form.getReference('project_name').Project_Name;
	var newv=g_form.getReference('project_name').Project_Name;
 alert('old');
	alert('newv');
   //Type appropriate comment here, and begin script below
   
}]]&gt;&lt;/script&gt;&lt;sys_class_name&gt;sys_script_client&lt;/sys_class_name&gt;&lt;sys_created_by&gt;admin&lt;/sys_created_by&gt;&lt;sys_created_on&gt;2022-03-18 05:37:32&lt;/sys_created_on&gt;&lt;sys_domain&gt;global&lt;/sys_domain&gt;&lt;sys_domain_path&gt;/&lt;/sys_domain_path&gt;&lt;sys_id&gt;9459207d1bd609105c68ec23604bcb42&lt;/sys_id&gt;&lt;sys_mod_count&gt;4&lt;/sys_mod_count&gt;&lt;sys_name&gt;Onchange &lt;/sys_name&gt;&lt;sys_overrides/&gt;&lt;sys_package display_value="Smart Management" source="x_775264_smart_man"&gt;0ad3d8e51b9ac5105c68ec23604bcb5f&lt;/sys_package&gt;&lt;sys_policy/&gt;&lt;sys_scope display_value="Smart Management"&gt;0ad3d8e51b9ac5105c68ec23604bcb5f&lt;/sys_scope&gt;&lt;sys_update_name&gt;sys_script_client_9459207d1bd609105c68ec23604bcb42&lt;/sys_update_name&gt;&lt;sys_updated_by&gt;admin&lt;/sys_updated_by&gt;&lt;sys_updated_on&gt;2022-03-18 06:27:57&lt;/sys_updated_on&gt;&lt;table&gt;x_775264_smart_man_project_details&lt;/table&gt;&lt;type&gt;onChange&lt;/type&gt;&lt;ui_type&gt;0&lt;/ui_type&gt;&lt;view/&gt;&lt;/sys_script_client&gt;&lt;/record_update&gt;</payload>
        <payload_hash>-914932404</payload_hash>
        <record_name>Onchange </record_name>
        <reverted_from/>
        <source>86d39c6d1b9ac5105c68ec23604bcba3</source>
        <source_table>sys_update_set</source_table>
        <state>previous</state>
        <sys_created_by>admin</sys_created_by>
        <sys_created_on>2022-03-18 06:27:57</sys_created_on>
        <sys_id>2f957cb51b1a09105c68ec23604bcb98</sys_id>
        <sys_mod_count>0</sys_mod_count>
        <sys_recorded_at>17f9bb61cab0000001</sys_recorded_at>
        <sys_updated_by>admin</sys_updated_by>
        <sys_updated_on>2022-03-18 06:27:57</sys_updated_on>
        <type>Client Script</type>
        <update_guid>67957cb5701a09107216606f3b7fda98</update_guid>
        <update_guid_history>67957cb5701a09107216606f3b7fda98:-914932404,27557cb58b1a0910cda3b6b12089a83c:-194451976,be7430b5ea1a09108233f7de556c980a:358257144,e95430b5a71a091048fb8123d7664105:229476696,b81aec393ad609109b6fca9e1641620d:436245425</update_guid_history>
    </sys_update_version>
    <sys_metadata_delete action="INSERT_OR_UPDATE">
        <sys_audit_delete/>
        <sys_class_name>sys_metadata_delete</sys_class_name>
        <sys_created_by>admin</sys_created_by>
        <sys_created_on>2022-03-18 06:33:54</sys_created_on>
        <sys_db_object display_value="" name="sys_script_client">sys_script_client</sys_db_object>
        <sys_id>3c3ba127e79f42e09782177c43392400</sys_id>
        <sys_metadata>9459207d1bd609105c68ec23604bcb42</sys_metadata>
        <sys_mod_count>0</sys_mod_count>
        <sys_name>Onchange </sys_name>
        <sys_package display_value="Smart Management" source="x_775264_smart_man">0ad3d8e51b9ac5105c68ec23604bcb5f</sys_package>
        <sys_parent display_value="Project details">ac8d14651bdac5105c68ec23604bcb68</sys_parent>
        <sys_policy/>
        <sys_scope display_value="Smart Management">0ad3d8e51b9ac5105c68ec23604bcb5f</sys_scope>
        <sys_scope_delete display_value="">0730c331f99a43149695982f1c6f9c10</sys_scope_delete>
        <sys_update_name>sys_script_client_9459207d1bd609105c68ec23604bcb42</sys_update_name>
        <sys_update_version display_value="sys_script_client_9459207d1bd609105c68ec23604bcb42">2f957cb51b1a09105c68ec23604bcb98</sys_update_version>
        <sys_updated_by>admin</sys_updated_by>
        <sys_updated_on>2022-03-18 06:33:54</sys_updated_on>
    </sys_metadata_delete>
</record_update>
